<?xml version="1.0" encoding="utf-8" ?>
<dwsync>
<file name="theme_styles.css" server="Z:/Skaters/" local="130868781128715797" remote="130868781120000000" Dst="0" />
<file name="wizard.css" server="Z:/Skaters/" local="130659422380000000" remote="130659422380000000" Dst="0" />
<file name="theme_styles.css" server="Y:/Skaters/" local="130868781128715797" remote="130868781120000000" Dst="0" />
<file name="wizard.css" server="Y:/Skaters/" local="130659422380000000" remote="130659422380000000" Dst="0" />
<file name="theme_styles.css" server="Z:/Skaters_test/" local="130868781128715797" remote="130868781120000000" Dst="0" />
<file name="wizard.css" server="Z:/Skaters_test/" local="130659422380000000" remote="130659422380000000" Dst="0" />
<file name="theme_styles.css" server="Z:/Skater_final/" local="130868781128715797" remote="130868781120000000" Dst="0" />
<file name="wizard.css" server="Z:/Skater_final/" local="130659422380000000" remote="130659422380000000" Dst="0" />
<file name="theme_styles.css" server="Z:/Skater_final1/" local="130868781128715797" remote="130868781120000000" Dst="0" />
<file name="wizard.css" server="Z:/Skater_final1/" local="130659422380000000" remote="130659422380000000" Dst="0" />
</dwsync>